README.rst
setup.py
toxgen.py
toxgen.egg-info/PKG-INFO
toxgen.egg-info/SOURCES.txt
toxgen.egg-info/dependency_links.txt
toxgen.egg-info/requires.txt
toxgen.egg-info/top_level.txt