Metadata-Version: 1.1
Name: toxgen
Version: 0.1
Summary: Tox.ini generator
Home-page: https://bitbucket.org/cdevienne/toxgen
Author: Christophe de Vienne
Author-email: cdevienne@gmail.com
License: UNKNOWN
Keywords: tox template generator combinations test
Platform: UNKNOWN
Classifier: Development Status :: 4 - Beta
Classifier: Environment :: Console
Classifier: Topic :: Utilities
Classifier: Programming Language :: Python
Classifier: Programming Language :: Python :: 2.6
Classifier: Programming Language :: Python :: 2.7
Classifier: Programming Language :: Python :: 3.3
